README.md
setup.py
trading_com_dados/__init__.py
trading_com_dados/opcoes.py
trading_com_dados.egg-info/PKG-INFO
trading_com_dados.egg-info/SOURCES.txt
trading_com_dados.egg-info/dependency_links.txt
trading_com_dados.egg-info/top_level.txt